{
    "name": "Device Center",
    "isPlayStore": true,
    "channel": {
        "debug": {
            "version_code": "330000151",
            "changelog": "Android Emulator application debug testing.",
            "isOptional": true,
            "downloadUrl": ""
        },
        "release": {
            "version_code": "330000151",
            "changelog": "With this update, support for Android 15 Beta has been included.",
            "isOptional": true,
            "downloadUrl": ""
        },
        "beta": {
            "version_code": "330000151",
            "changelog": "With this update, support for Android 15 Beta has been included.",
            "isOptional": true,
            "downloadUrl": ""
        },
        "dev": {
            "version_code": "330000151",
            "changelog": "With this update, support for Android 15 Beta has been included.",
            "isOptional": true,
            "downloadUrl": ""
        }
    }
}
